openedx_companion_auth/__init__.py
openedx_companion_auth/apps.py
openedx_companion_auth/manage.py
openedx_companion_auth/middleware.py
openedx_companion_auth/urls.py
openedx_companion_auth/settings/__init__.py
openedx_companion_auth/settings/common.py
openedx_companion_auth/settings/production.py
openedx_companion_auth/settings/test.py
openedx_companion_auth-1.2.0.dist-info/METADATA
openedx_companion_auth-1.2.0.dist-info/WHEEL
openedx_companion_auth-1.2.0.dist-info/entry_points.txt
openedx_companion_auth-1.2.0.dist-info/licenses/LICENSE
openedx_companion_auth-1.2.0.dist-info/RECORD
