Metadata-Version: 2.4
Name: openedx-companion-auth
Version: 1.2.0
Summary: A package to add login redirection from Open edX to MIT applications
Author: MIT Office of Digital Learning
License-Expression: BSD-3-Clause
License-File: LICENSE
Keywords: Python,edx
Requires-Python: >=3.11
Requires-Dist: django>=4.0
Requires-Dist: djangorestframework>=3.14.0
Requires-Dist: edx-django-utils>3.0.0
